{
    "id": "teddy_12",
    "uid": "ad2b755dc21a4d71b4b648519413b088",
    "name": "Teddy",
    "type": "person",
    "created": "2025-08-24T03:55:41.118822+00:00",
    "updated": "2025-08-24T03:55:48.663246+00:00",
    "entries": [
        {
            "created": "2025-08-24T03:55:48.663246+00:00",
            "updated": "2025-08-24T03:55:48.663246+00:00",
            "time": {
                "label_type": "life_stage",
                "confidence": 100,
                "subvalue": "childhood"
            },
            "time_normalised": {
                "kind": "life_stage",
                "start_iso": null,
                "end_iso": null,
                "start_ts": null,
                "end_ts": null,
                "precision": "approx",
                "age_years": 6.5,
                "notes": "Life stage 'childhood' (no reference date — absolute bounds unknown)"
            }
        }
    ]
}